{
	"columns": [
		{
			"column_name": "admins_id",
			"label": "ID",
			"position": 10,
			"filter": {
				"type": "range"
			},
			"renderer": null,
			"db_table_column": true,
			"sortable": true,
			"primary_key": true
		},
		{
			"column_name": "email",
			"label": "E-Mail",
			"position": 20,
			"filter": {
				"type": "text"
			},
			"renderer": null,
			"db_table_column": true,
			"sortable": true
		},
		{
			"column_name": "username",
			"label": "Username",
			"position": 30,
			"filter": {
				"type": "text"
			},
			"renderer": null,
			"db_table_column": true,
			"sortable": true
		},
		{
			"column_name": "firstname",
			"label": "Firstname",
			"position": 40,
			"filter": {
				"type": "text"
			},
			"renderer": null,
			"db_table_column": true,
			"sortable": true
		},
		{
			"column_name": "lastname",
			"label": "Lastname",
			"position": 50,
			"filter": {
				"type": "text"
			},
			"renderer": null,
			"db_table_column": true,
			"sortable": true
		},
		{
			"column_name": "status",
			"label": "Status",
			"position": 60,
			"filter": {
				"type": "select",
				"option": "Opoink\\Bmodule\\Block\\Admin\\UiComponents\\DataProvider\\AdminUserStatus"
			},
			"renderer": null,
			"db_table_column": true,
			"sortable": true
		},
		{
			"column_name": "lang",
			"label": "Language",
			"position": 70,
			"filter": {
				"type": "text"
			},
			"renderer": null,
			"db_table_column": true,
			"sortable": true
		},
		{
			"column_name": "action",
			"label": "Action",
			"renderer": "Opoink\\Bmodule\\Block\\Admin\\UiComponents\\Renderer\\AdminAdminuserIndexIndexGridAction",
			"db_table_column": false,
			"sortable": false
		}
	],
	"model": {
		"priority": 100,
		"class":"Opoink\\Bmodule\\Model\\UiComponent\\Grid\\AdminAdminuserIndexIndexGrid"
	},
	"main_table": "admins",
	"limit": [20,50,100,200,500],
	"top_buttons": {
		"filters": true,
		"export": true
	}
}